MANIFEST.in
setup.cfg
setup.py
tw/__init__.py
tw.yui.egg-info/PKG-INFO
tw.yui.egg-info/SOURCES.txt
tw.yui.egg-info/dependency_links.txt
tw.yui.egg-info/entry_points.txt
tw.yui.egg-info/namespace_packages.txt
tw.yui.egg-info/not-zip-safe
tw.yui.egg-info/requires.txt
tw.yui.egg-info/top_level.txt
tw/yui/__init__.py
tw/yui/autocomplete.py
tw/yui/base.py
tw/yui/defaults.py
tw/yui/release.py
tw/yui/samples.py
tw/yui/uploader.py
tw/yui/widgets.py
tw/yui/yuitest.py
tw/yui/static/.DS_Store
tw/yui/static/__init__.py
tw/yui/static/2.7.0/build/animation/animation-debug.js
tw/yui/static/2.7.0/build/animation/animation-min.js
tw/yui/static/2.7.0/build/animation/animation.js
tw/yui/static/2.7.0/build/assets/skins/sam/ajax-loader.gif
tw/yui/static/2.7.0/build/assets/skins/sam/asc.gif
tw/yui/static/2.7.0/build/assets/skins/sam/autocomplete.css
tw/yui/static/2.7.0/build/assets/skins/sam/bg-h.gif
tw/yui/static/2.7.0/build/assets/skins/sam/bg-v.gif
tw/yui/static/2.7.0/build/assets/skins/sam/blankimage.png
tw/yui/static/2.7.0/build/assets/skins/sam/button.css
tw/yui/static/2.7.0/build/assets/skins/sam/calendar.css
tw/yui/static/2.7.0/build/assets/skins/sam/carousel.css
tw/yui/static/2.7.0/build/assets/skins/sam/colorpicker.css
tw/yui/static/2.7.0/build/assets/skins/sam/container.css
tw/yui/static/2.7.0/build/assets/skins/sam/datatable.css
tw/yui/static/2.7.0/build/assets/skins/sam/desc.gif
tw/yui/static/2.7.0/build/assets/skins/sam/dt-arrow-dn.png
tw/yui/static/2.7.0/build/assets/skins/sam/dt-arrow-up.png
tw/yui/static/2.7.0/build/assets/skins/sam/editor-knob.gif
tw/yui/static/2.7.0/build/assets/skins/sam/editor-sprite-active.gif
tw/yui/static/2.7.0/build/assets/skins/sam/editor-sprite.gif
tw/yui/static/2.7.0/build/assets/skins/sam/editor.css
tw/yui/static/2.7.0/build/assets/skins/sam/header_background.png
tw/yui/static/2.7.0/build/assets/skins/sam/hue_bg.png
tw/yui/static/2.7.0/build/assets/skins/sam/imagecropper.css
tw/yui/static/2.7.0/build/assets/skins/sam/layout.css
tw/yui/static/2.7.0/build/assets/skins/sam/layout_sprite.png
tw/yui/static/2.7.0/build/assets/skins/sam/loading.gif
tw/yui/static/2.7.0/build/assets/skins/sam/logger.css
tw/yui/static/2.7.0/build/assets/skins/sam/menu-button-arrow-disabled.png
